cargo_t_x64_win_msvc_nightly_p1/__init__.py
cargo_t_x64_win_msvc_nightly_p1/data/LICENSE-APACHE
cargo_t_x64_win_msvc_nightly_p1/data/LICENSE-MIT
cargo_t_x64_win_msvc_nightly_p1/data/LICENSE-THIRD-PARTY
cargo_t_x64_win_msvc_nightly_p1/data/README.md
cargo_t_x64_win_msvc_nightly_p1/data/builder-config
cargo_t_x64_win_msvc_nightly_p1/data/components
cargo_t_x64_win_msvc_nightly_p1/data/git-commit-hash
cargo_t_x64_win_msvc_nightly_p1/data/git-commit-info
cargo_t_x64_win_msvc_nightly_p1/data/install.sh
cargo_t_x64_win_msvc_nightly_p1/data/rust-installer-version
cargo_t_x64_win_msvc_nightly_p1/data/version
cargo_t_x64_win_msvc_nightly_p1/data/cargo/manifest.in
cargo_t_x64_win_msvc_nightly_p1/data/cargo/bin/cargo.exe
cargo_t_x64_win_msvc_nightly_p1/data/cargo/bin/cargo.pdb
cargo_t_x64_win_msvc_nightly_p1/data/cargo/etc/bash_completion.d/cargo
cargo_t_x64_win_msvc_nightly_p1/data/cargo/share/doc/cargo/LICENSE-APACHE
cargo_t_x64_win_msvc_nightly_p1/data/cargo/share/doc/cargo/LICENSE-MIT
cargo_t_x64_win_msvc_nightly_p1/data/cargo/share/doc/cargo/LICENSE-THIRD-PARTY
cargo_t_x64_win_msvc_nightly_p1/data/cargo/share/doc/cargo/README.md
cargo_t_x64_win_msvc_nightly_p1/data/cargo/share/man/man1/cargo-add.1
cargo_t_x64_win_msvc_nightly_p1/data/cargo/share/man/man1/cargo-bench.1
cargo_t_x64_win_msvc_nightly_p1/data/cargo/share/man/man1/cargo-build.1
cargo_t_x64_win_msvc_nightly_p1/data/cargo/share/man/man1/cargo-check.1
cargo_t_x64_win_msvc_nightly_p1/data/cargo/share/man/man1/cargo-clean.1
cargo_t_x64_win_msvc_nightly_p1/data/cargo/share/man/man1/cargo-doc.1
cargo_t_x64_win_msvc_nightly_p1/data/cargo/share/man/man1/cargo-fetch.1
cargo_t_x64_win_msvc_nightly_p1/data/cargo/share/man/man1/cargo-fix.1
cargo_t_x64_win_msvc_nightly_p1/data/cargo/share/man/man1/cargo-generate-lockfile.1
cargo_t_x64_win_msvc_nightly_p1/data/cargo/share/man/man1/cargo-help.1
cargo_t_x64_win_msvc_nightly_p1/data/cargo/share/man/man1/cargo-info.1
cargo_t_x64_win_msvc_nightly_p1-0.91.0.dist-info/METADATA
cargo_t_x64_win_msvc_nightly_p1-0.91.0.dist-info/WHEEL
cargo_t_x64_win_msvc_nightly_p1-0.91.0.dist-info/top_level.txt
cargo_t_x64_win_msvc_nightly_p1-0.91.0.dist-info/RECORD
