Metadata-Version: 2.4
Name: cargo_t_x64_win_msvc_nightly_p1
Version: 0.91.0
Summary: Segment cargo.target.x86_64-pc-windows-msvc part p1
License: MIT
